directory_structure_py/__init__.py
directory_structure_py/__main__.py
directory_structure_py/_version.py
directory_structure_py/constants.py
directory_structure_py/conversion.py
directory_structure_py/get_metadata.py
directory_structure_py/main.py
directory_structure_py/rocrate_models.py
directory_structure_py/config/logging.json
directory_structure_py/docs/favicon.ico
directory_structure_py/templates/preview_template.html.j2
directory_structure_py-0.2.6.data/data/directory_structure_py/config/logging.json
directory_structure_py-0.2.6.data/data/directory_structure_py/docs/favicon.ico
directory_structure_py-0.2.6.data/data/directory_structure_py/templates/preview_template.html.j2
directory_structure_py-0.2.6.dist-info/LICENSE
directory_structure_py-0.2.6.dist-info/METADATA
directory_structure_py-0.2.6.dist-info/WHEEL
directory_structure_py-0.2.6.dist-info/entry_points.txt
directory_structure_py-0.2.6.dist-info/top_level.txt
directory_structure_py-0.2.6.dist-info/RECORD
