Metadata-Version: 2.1
Name: directory-structure-py
Version: 0.2.6
Summary: Python function collecting the metadata of a directory and its contents
Author-email: Surpris <take90-it09-easy27@outlook.jp>
License:                                  Apache License
Project-URL: Homepage, https://github.com/Surpris/directory-structure-py
Project-URL: Repository, https://github.com/Surpris/directory-structure-py
Project-URL: Bug Tracker, https://github.com/Surpris/directory-structure-py/issues
Classifier: Development Status :: 3 - Alpha
Classifier: Intended Audience :: Developers
Classifier: Programming Language :: Python :: 3.12
Classifier: Operating System :: OS Independent
Classifier: Operating System :: POSIX
Classifier: Operating System :: MacOS
Classifier: Operating System :: POSIX :: Linux
Classifier: Operating System :: Microsoft :: Windows
Classifier: Topic :: Software Development :: Libraries :: Python Modules
Classifier: License :: OSI Approved :: Apache Software License
Requires-Python: >=3.12
License-File: LICENSE
Requires-Dist: rocrate
Provides-Extra: dev
Requires-Dist: line_profiler; extra == "dev"
Requires-Dist: pyinstaller; extra == "dev"
Requires-Dist: pytest; extra == "dev"
Requires-Dist: pylint; extra == "dev"
Requires-Dist: autopep8; extra == "dev"
Requires-Dist: flake8; extra == "dev"
Requires-Dist: jupyter; extra == "dev"
Requires-Dist: jupyterlab; extra == "dev"
Requires-Dist: twine; extra == "dev"
